databag/__init__.py
databag/main.py
databag/orm/__init__.py
databag/orm/field.py
databag/orm/model.py
databag-1.5.0.dist-info/LICENSE
databag-1.5.0.dist-info/METADATA
databag-1.5.0.dist-info/WHEEL
databag-1.5.0.dist-info/top_level.txt
databag-1.5.0.dist-info/RECORD
