Metadata-Version: 2.1
Name: databag
Version: 1.5.0
Summary: Put your data in a bag and get it back out again
Home-page: https://github.com/nod/databag
Author: Jeremy Kelley
Author-email: jeremy@33ad.org
License: UNKNOWN
Platform: UNKNOWN
Classifier: License :: OSI Approved :: MIT License
Classifier: Programming Language :: Python :: 3
Classifier: Topic :: Utilities
Classifier: Topic :: Database
Requires-Python: >=3.6
